gdmath/__init__.py
gdmath-1.5.4.dist-info/LICENSE.txt
gdmath-1.5.4.dist-info/METADATA
gdmath-1.5.4.dist-info/WHEEL
gdmath-1.5.4.dist-info/top_level.txt
gdmath-1.5.4.dist-info/RECORD
