Metadata-Version: 2.1
Name: gdmath
Version: 1.5.4
Summary: GdMath: a fast spatial math library [RENAMED TO: Spatium]
Author-email: shBLOCK <shblock3@gmail.com>
License: 
Project-URL: Source, https://github.com/shBLOCK/spatium
Project-URL: Documentation, https://github.com/shBLOCK/spatium/wiki
Project-URL: Issue Tracker, https://github.com/shBLOCK/spatium/issues
Keywords: vector,linear algebra,math,math library,spatial,spatial math,gamedev,game development
Classifier: Programming Language :: Cython
Classifier: Programming Language :: Python
Classifier: Programming Language :: Python :: 3
Classifier: Programming Language :: Python :: 3.9
Classifier: Programming Language :: Python :: 3.10
Classifier: Programming Language :: Python :: 3.11
Classifier: Programming Language :: Python :: 3.12
Classifier: Programming Language :: Python :: Implementation :: CPython
Classifier: Programming Language :: Python :: Implementation :: PyPy
Classifier: Typing :: Typed
Classifier: Operating System :: OS Independent
Classifier: Operating System :: MacOS
Classifier: Operating System :: Microsoft :: Windows
Classifier: Operating System :: POSIX
Classifier: Operating System :: Unix
Classifier: License :: OSI Approved :: GNU Lesser General Public License v3 (LGPLv3)
Classifier: Intended Audience :: Developers
Classifier: Intended Audience :: Science/Research
Classifier: Topic :: Software Development :: Libraries :: Python Modules
Classifier: Topic :: Scientific/Engineering :: Mathematics
Classifier: Topic :: Software Development :: Libraries :: Python Modules
Classifier: Topic :: Software Development :: Code Generators
Classifier: Topic :: Games/Entertainment
Classifier: Topic :: Multimedia :: Graphics
Requires-Python: >=3.9
License-File: LICENSE.txt
Requires-Dist: spatium
